xl_reports.py
xl_reports-0.1.3.dist-info/LICENSE
xl_reports-0.1.3.dist-info/WHEEL
xl_reports-0.1.3.dist-info/METADATA
xl_reports-0.1.3.dist-info/RECORD
